nkdv/__init__.py
nkdv/compute_nkdv.py
nkdv/nkdv.dll
nkdv/nkdv.py
nkdv/nkdv_mac.so
nkdv-0.0.6.dist-info/LICENSE.txt
nkdv-0.0.6.dist-info/METADATA
nkdv-0.0.6.dist-info/WHEEL
nkdv-0.0.6.dist-info/top_level.txt
nkdv-0.0.6.dist-info/RECORD
